{
  "generated_at": "2026-05-02T05:27:11.070146+00:00",
  "date": "2026-05-02",
  "platform_score": 73,
  "healthy_repos": 3,
  "failed_repos": 12,
  "total_repos": 15,
  "failures": [
    "pr-autopilot",
    "runbook-gen",
    "mcp-compliance-grc",
    "TeamHealthRadar",
    "PlatformSLOBoard",
    "TechDebtLedger",
    "IncidentPilot",
    "DataPipelineAgent",
    "BoardroomBrief",
    "innersource-scorecard",
    "service-catalog-sync",
    "platform-maturity-model"
  ],
  "issues_opened": 0,
  "repos": [
    {
      "repo": "repoforge",
      "score": 80,
      "status": "healthy",
      "agent_ok": false,
      "ci_ok": true
    },
    {
      "repo": "pr-autopilot",
      "score": 70,
      "status": "degraded",
      "agent_ok": true,
      "ci_ok": false
    },
    {
      "repo": "runbook-gen",
      "score": 70,
      "status": "degraded",
      "agent_ok": true,
      "ci_ok": false
    },
    {
      "repo": "mcp-incident-intel",
      "score": 100,
      "status": "healthy",
      "agent_ok": true,
      "ci_ok": true
    },
    {
      "repo": "mcp-compliance-grc",
      "score": 70,
      "status": "degraded",
      "agent_ok": true,
      "ci_ok": false
    },
    {
      "repo": "mcp-developer-portal",
      "score": 100,
      "status": "healthy",
      "agent_ok": true,
      "ci_ok": true
    },
    {
      "repo": "TeamHealthRadar",
      "score": 70,
      "status": "degraded",
      "agent_ok": true,
      "ci_ok": false
    },
    {
      "repo": "PlatformSLOBoard",
      "score": 70,
      "status": "degraded",
      "agent_ok": true,
      "ci_ok": false
    },
    {
      "repo": "TechDebtLedger",
      "score": 70,
      "status": "degraded",
      "agent_ok": true,
      "ci_ok": false
    },
    {
      "repo": "IncidentPilot",
      "score": 70,
      "status": "degraded",
      "agent_ok": true,
      "ci_ok": false
    },
    {
      "repo": "DataPipelineAgent",
      "score": 70,
      "status": "degraded",
      "agent_ok": true,
      "ci_ok": false
    },
    {
      "repo": "BoardroomBrief",
      "score": 50,
      "status": "degraded",
      "agent_ok": false,
      "ci_ok": false
    },
    {
      "repo": "innersource-scorecard",
      "score": 70,
      "status": "degraded",
      "agent_ok": true,
      "ci_ok": false
    },
    {
      "repo": "service-catalog-sync",
      "score": 70,
      "status": "degraded",
      "agent_ok": true,
      "ci_ok": false
    },
    {
      "repo": "platform-maturity-model",
      "score": 70,
      "status": "degraded",
      "agent_ok": true,
      "ci_ok": false
    }
  ]
}